xraydb/__init__.py
xraydb/chemparser.py
xraydb/materials.dat
xraydb/materials.py
xraydb/utils.py
xraydb/version.py
xraydb/xray.py
xraydb/xraydb.py
xraydb/xraydb.sqlite
xraydb-4.5.4.dist-info/LICENSE
xraydb-4.5.4.dist-info/METADATA
xraydb-4.5.4.dist-info/WHEEL
xraydb-4.5.4.dist-info/top_level.txt
xraydb-4.5.4.dist-info/RECORD
